README.rst
setup.py
sports_players/Basketball_Player.py
sports_players/General_Player.py
sports_players/__init__.py
sports_players.egg-info/PKG-INFO
sports_players.egg-info/SOURCES.txt
sports_players.egg-info/dependency_links.txt
sports_players.egg-info/not-zip-safe
sports_players.egg-info/requires.txt
sports_players.egg-info/top_level.txt