Metadata-Version: 2.1
Name: sports-players
Version: 1.2.1
Summary: Sports Players Objects
Home-page: UNKNOWN
Author: Frantz Paul
Author-email: fpaul787@gmail.com
License: UNKNOWN
Platform: UNKNOWN
